main_adder.v
`timescale 1ns / 1ps
`define SCR1_XLEN  32 // operand length
`define SCR1_IALU_CMD_ADD  0 // ADD code
`define SCR1_IALU_CMD_SUB  1 // SUB code
module main_adder
(
    //input clk,
    input    [`SCR1_XLEN-1:0]  exu2ialu_main_op1_i,        // main ALU 1st operand
    input    [`SCR1_XLEN-1:0]  exu2ialu_main_op2_i,        // main ALU 2nd operand
    input    exu2ialu_cmd_i,             // IALU command
    output  [`SCR1_XLEN-1:0] ialu2exu_main_res_o,        // main ALU result
    output  reg  ialu2exu_cmp_res_o,    // IALU comparison result
    output reg main_sum_pos_ovflw, // Operation causes positive overflow
    output reg main_sum_neg_ovflw, // Operation causes negative overflow
    output reg  flag_z,   // Zero
    output reg  flag_s,      // Sign
    output reg  flag_o,      // Overflow
    output reg  flag_c,   // Carry
    output reg  main_ops_diff_sgn, // Main adder operands have different signs
    output reg  main_ops_non_zero // Both main adder operands are NOT 0
    );

reg [`SCR1_XLEN:0] main_sum_res;       // Main adder result

initial begin // init block
    main_ops_diff_sgn = 0;
    main_ops_non_zero = 0;
    main_sum_pos_ovflw = 0;
    main_sum_neg_ovflw = 0;
    flag_z = 0;
    flag_s = 0;
    flag_o = 0;
    flag_c = 0;
end

assign ialu2exu_main_res_o = main_sum_res[`SCR1_XLEN-1:0]; // assigning temproray result to 32'b output result

always@ * // always_comb block
begin
    main_sum_res = (exu2ialu_cmd_i != 0)
                 ? ({1'b0, exu2ialu_main_op1_i} - {1'b0, exu2ialu_main_op2_i})   // Subtraction and comparison
                 : ({1'b0, exu2ialu_main_op1_i} + {1'b0, exu2ialu_main_op2_i});  // Addition

    main_sum_pos_ovflw = ~exu2ialu_main_op1_i[`SCR1_XLEN-1]
                       &  exu2ialu_main_op2_i[`SCR1_XLEN-1]
                       &  main_sum_res[`SCR1_XLEN-1];
    main_sum_neg_ovflw =  exu2ialu_main_op1_i[`SCR1_XLEN-1]
                       & ~exu2ialu_main_op2_i[`SCR1_XLEN-1]
                       & ~main_sum_res[`SCR1_XLEN-1];
    main_ops_diff_sgn  = (~exu2ialu_main_op1_i[`SCR1_XLEN-1]
		       & exu2ialu_main_op2_i[`SCR1_XLEN-1])
                       | (exu2ialu_main_op1_i[`SCR1_XLEN-1]
                       & ~exu2ialu_main_op2_i[`SCR1_XLEN-1]);
    main_ops_non_zero  = (|exu2ialu_main_op1_i[`SCR1_XLEN-1:0])
                       & (|exu2ialu_main_op2_i[`SCR1_XLEN-1:0]);

    flag_c = main_sum_res[`SCR1_XLEN];
    flag_z = ~|main_sum_res[`SCR1_XLEN-1:0];
    flag_s = main_sum_res[`SCR1_XLEN-1];
    flag_o = main_sum_pos_ovflw | main_sum_neg_ovflw;
end
endmodule

main_adder_test.v
`timescale 1ns / 1ps

module main_adder_test(
    input    [`SCR1_XLEN-1:0]  exu2ialu_main_op1_i,        // main ALU 1st operand
    input    [`SCR1_XLEN-1:0]  exu2ialu_main_op2_i,        // main ALU 2nd operand
    input    exu2ialu_cmd_i,             // IALU command
    output  [`SCR1_XLEN-1:0] ialu2exu_main_res_o,        // main ALU result
    output  reg  ialu2exu_cmp_res_o,    // IALU comparison result
    output  reg  main_sum_pos_ovflw,
    output  reg main_sum_neg_ovflw,
    output reg  flag_z,   // Zero
    output reg  flag_s,      // Sign
    output reg  flag_o,      // Overflow
    output reg  flag_c,      // Carry
    output reg  main_ops_diff_sgn, // Main adder operands have different signs
    output reg  main_ops_non_zero // Both main adder operands are NOT 0
    );

main_adder main_adder(
    .exu2ialu_main_op1_i(exu2ialu_main_op1_i),
    .exu2ialu_main_op2_i(exu2ialu_main_op2_i),
    .exu2ialu_cmd_i(exu2ialu_cmd_i),
    .ialu2exu_main_res_o(ialu2exu_main_res_o),
    .ialu2exu_cmp_res_o(ialu2exu_cmp_res_o),
    .main_sum_pos_ovflw(main_sum_pos_ovflw),
    .main_sum_neg_ovflw( main_sum_neg_ovflw),
    .flag_z(flag_z),
    .flag_s(flag_s),
    .flag_o(flag_o),
    .flag_c(flag_c),
    .main_ops_diff_sgn(main_ops_diff_sgn),
    .main_ops_non_zero(main_ops_non_zero)
);

initial begin
    $dumpfile("waves.vcd");
    $dumpvars;
end
endmodule

main_adder_waveform.vcd
$date
	Thu Nov 16 23:33:07 2023
$end
$version
	GTKWave Analyzer v3.3.103 (w)1999-2019 BSI
$end
$timescale
	1ps
$end
$scope module main_adder_test $end
$scope module main_adder $end
$var wire 1 " exu2ialu_cmd_i $end
$var wire 32 # exu2ialu_main_op1_i[31:0] $end
$var wire 32 $ exu2ialu_main_op2_i[31:0] $end
$var wire 32 * ialu2exu_main_res_o[31:0] $end
$var wire 1 % flag_c $end
$var wire 1 & flag_o $end
$var wire 1 ' flag_s $end
$var wire 1 ( flag_z $end
$var wire 1 ) ialu2exu_cmp_res_o $end
$var wire 1 + main_ops_diff_sgn $end
$var wire 1 , main_ops_non_zero $end
$var wire 1 - main_sum_neg_ovflw $end
$var wire 1 . main_sum_pos_ovflw $end
$var wire 33 / main_sum_res[32:0] $end
$upscope $end
$upscope $end
$enddefinitions $end
#0
$dumpvars
b100000000000000000000000000000000 /
1+
b0 *
0"
b1 #
1%
1(
x)
0'
0&
1,
b11111111111111111111111111111111 $
0.
0-
$end
#1000
0(
b1 *
b100000000000000000000000000000001 /
1"
b0 #
0,
#2000
1,
0"
b100000000000000000001111111111111 /
b1111111111111 *
b10000000000000 #
#3000
b11111111111011111111111111111111 #
b111111111111100000000000000000000 /
0+
1"
b11111111111100000000000000000000 *
1'
#4000
1+
b1 #
b10000000000000000000000000000001 /
0%
b10000000000000000000000000000001 *
0"
1&
1.
b10000000000000000000000000000000 $
#5000
b1111111111111111111111111111111 $
b100111111111111111111111111111111 /
0'
1-
b11000000000000000000000000000000 #
0.
b111111111111111111111111111111 *
1%
#6000
0%
0-
b11111111111111111111111111111111 /
b10101010101010101010101010101010 $
1'
b11111111111111111111111111111111 *
1.
b1010101010101010101010101010101 #
#7000
b10101000010001000010000011100001 #
b1010110011100000010100000100010 $
1-
b1010001110100111111100010111111 /
0.
b1010001110100111111100010111111 *
0'
1"
